MANIFEST.in
NEWS.txt
README.rst
setup.py
stock_gym/__init__.py
stock_gym.egg-info/PKG-INFO
stock_gym.egg-info/SOURCES.txt
stock_gym.egg-info/dependency_links.txt
stock_gym.egg-info/requires.txt
stock_gym.egg-info/top_level.txt
stock_gym/envs/__init__.py
stock_gym/envs/stocks/__init__.py
stock_gym/envs/stocks/actions.py
stock_gym/envs/stocks/basic.py
stock_gym/envs/stocks/imarket.py
stock_gym/envs/stocks/mixins.py