Metadata-Version: 1.0
Name: stock-gym
Version: 0.3
Summary: An OpenAI Gym environment for stock market data
Home-page: https://github.com/karma0/stock_gym.git
Author: Bobby
Author-email: karma0@gmail.com
License: MIT
Keywords: openai-gym-environments openai-gym openai
Platform: UNKNOWN
